setup.py
keen_csv/__init__.py
keen_csv/client.py
keen_csv/container.py
keen_csv.egg-info/PKG-INFO
keen_csv.egg-info/SOURCES.txt
keen_csv.egg-info/dependency_links.txt
keen_csv.egg-info/requires.txt
keen_csv.egg-info/top_level.txt